helcim/__init__.py
helcim/admin.py
helcim/apps.py
helcim/bridge_oscar.py
helcim/conversions.py
helcim/exceptions.py
helcim/gateway.py
helcim/mixins.py
helcim/models.py
helcim/settings.py
helcim/urls.py
helcim/views.py
helcim/migrations/0001_initial.py
helcim/migrations/0002_token_update_v2.py
helcim/migrations/0003_add_user_to_transaction.py
helcim/migrations/0004_add_verified_type.py
helcim/migrations/__init__.py
helcim/static/helcim/amex.png
helcim/static/helcim/amex.svg
helcim/static/helcim/discover.png
helcim/static/helcim/discover.svg
helcim/static/helcim/mastercard.png
helcim/static/helcim/mastercard.svg
helcim/static/helcim/placeholder.png
helcim/static/helcim/placeholder.svg
helcim/static/helcim/visa.png
helcim/static/helcim/visa.svg
helcim/templates/helcim/token_delete.html
helcim/templates/helcim/token_list.html
helcim/templates/helcim/transaction_detail.html
helcim/templates/helcim/transaction_list.html
django_helcim-0.9.1.dist-info/COPYING
django_helcim-0.9.1.dist-info/LICENSE
django_helcim-0.9.1.dist-info/METADATA
django_helcim-0.9.1.dist-info/WHEEL
django_helcim-0.9.1.dist-info/top_level.txt
django_helcim-0.9.1.dist-info/RECORD
