Metadata-Version: 2.1
Name: django-helcim
Version: 0.9.1
Summary: A Django-based integration with the Helcim Commerce API.
Home-page: https://github.com/studybuffalo/django-helcim
Author: Joshua Torrance
Author-email: studybuffalo@gmail.com
License: UNKNOWN
Project-URL: Documentation, https://django-helcim.readthedocs.io/en/latest/
Project-URL: Source code, https://github.com/studybuffalo/django-helcim
Project-URL: Issues, https://github.com/studybuffalo/django-helcim/issues
Keywords: Django,Helcim,Oscar,Payment
Platform: linux
Platform: windows
Classifier: Development Status :: 4 - Beta
Classifier: Environment :: Web Environment
Classifier: Framework :: Django :: 1.11
Classifier: Framework :: Django :: 2.2
Classifier: Framework :: Django :: 3.0
Classifier: Intended Audience :: Developers
Classifier: License :: OSI Approved :: GNU General Public License v3 (GPLv3)
Classifier: Operating System :: Unix
Classifier: Programming Language :: Python :: 3
Classifier: Programming Language :: Python :: 3.5
Classifier: Programming Language :: Python :: 3.6
Classifier: Programming Language :: Python :: 3.7
Classifier: Programming Language :: Python :: 3.8
Classifier: Topic :: Other/Nonlisted Topic
Requires-Dist: django (>=1.11)
Requires-Dist: requests (>=2.0)
Requires-Dist: xmltodict (>=0.11)
Provides-Extra: oscar
Requires-Dist: django-oscar (<2.1,>=1.6) ; extra == 'oscar'
